ament_cmake_cppcheck/_dummy.cpython-314-x86_64-linux-gnu.so
ros_ament_cmake_cppcheck-0.17.3.data/data/share/ament_cmake_cppcheck/local_setup.bash
ros_ament_cmake_cppcheck-0.17.3.data/data/share/ament_cmake_cppcheck/local_setup.dsv
ros_ament_cmake_cppcheck-0.17.3.data/data/share/ament_cmake_cppcheck/local_setup.sh
ros_ament_cmake_cppcheck-0.17.3.data/data/share/ament_cmake_cppcheck/local_setup.zsh
ros_ament_cmake_cppcheck-0.17.3.data/data/share/ament_cmake_cppcheck/package.dsv
ros_ament_cmake_cppcheck-0.17.3.data/data/share/ament_cmake_cppcheck/package.xml
ros_ament_cmake_cppcheck-0.17.3.data/data/share/ament_cmake_cppcheck/cmake/ament_cmake_cppcheck-extras.cmake
ros_ament_cmake_cppcheck-0.17.3.data/data/share/ament_cmake_cppcheck/cmake/ament_cmake_cppcheckConfig-version.cmake
ros_ament_cmake_cppcheck-0.17.3.data/data/share/ament_cmake_cppcheck/cmake/ament_cmake_cppcheckConfig.cmake
ros_ament_cmake_cppcheck-0.17.3.data/data/share/ament_cmake_cppcheck/cmake/ament_cmake_cppcheck_lint_hook.cmake
ros_ament_cmake_cppcheck-0.17.3.data/data/share/ament_cmake_cppcheck/cmake/ament_cppcheck.cmake
ros_ament_cmake_cppcheck-0.17.3.data/data/share/ament_cmake_cppcheck/environment/ament_prefix_path.dsv
ros_ament_cmake_cppcheck-0.17.3.data/data/share/ament_cmake_cppcheck/environment/ament_prefix_path.sh
ros_ament_cmake_cppcheck-0.17.3.data/data/share/ament_cmake_cppcheck/environment/path.dsv
ros_ament_cmake_cppcheck-0.17.3.data/data/share/ament_cmake_cppcheck/environment/path.sh
ros_ament_cmake_cppcheck-0.17.3.data/data/share/ament_index/resource_index/package_run_dependencies/ament_cmake_cppcheck
ros_ament_cmake_cppcheck-0.17.3.data/data/share/ament_index/resource_index/packages/ament_cmake_cppcheck
ros_ament_cmake_cppcheck-0.17.3.data/data/share/ament_index/resource_index/parent_prefix_path/ament_cmake_cppcheck
ros_ament_cmake_cppcheck-0.17.3.dist-info/METADATA
ros_ament_cmake_cppcheck-0.17.3.dist-info/WHEEL
ros_ament_cmake_cppcheck-0.17.3.dist-info/top_level.txt
ros_ament_cmake_cppcheck-0.17.3.dist-info/RECORD
