Metadata-Version: 2.4
Name: ros-ament-cmake-cppcheck
Version: 0.17.3
Summary: Wheel for the ament_cmake_cppcheck (ros-ament-cmake-cppcheck) ROS 2 package.
Dynamic: description
Dynamic: description-content-type
Dynamic: summary
